hippo_csv/__init__.py
hippo_csv/csv_utilities.py
hippo_csv-0.1.0.dist-info/METADATA
hippo_csv-0.1.0.dist-info/WHEEL
hippo_csv-0.1.0.dist-info/top_level.txt
hippo_csv-0.1.0.dist-info/RECORD
