Metadata-Version: 2.4
Name: hippo_csv
Version: 0.1.0
Summary: Professional CSV utilities by King Hippopotamus
Author-email: King Hippopotamus  <king.hippopotamus@yahoo.com>
License: MIT
Keywords: csv,utilities,pandas,data,hippo
Classifier: Programming Language :: Python :: 3
Classifier: License :: OSI Approved :: MIT License
Classifier: Operating System :: OS Independent
Classifier: Intended Audience :: Developers
Classifier: Topic :: Software Development :: Libraries
Classifier: Topic :: Utilities
Requires-Python: >=3.8
Requires-Dist: pandas<3.0.0,>=2.2.0
